{
  "kind": "collectionType",
  "collectionName": "questions",
  "info": {
    "singularName": "question",
    "pluralName": "questions",
    "displayName": "Question",
    "description": ""
  },
  "options": {
    "draftAndPublish": false
  },
  "pluginOptions": {},
  "attributes": {
    "topic": {
      "type": "text",
      "required": true
    },
    "a": {
      "type": "string",
      "required": true
    },
    "type": {
      "type": "enumeration",
      "enum": [
        "N2",
        "N3",
        "N4",
        "N5"
      ],
      "required": true
    },
    "b": {
      "type": "string",
      "required": true
    },
    "c": {
      "type": "string",
      "required": true
    },
    "d": {
      "type": "string",
      "required": true
    },
    "answerCorrect": {
      "type": "enumeration",
      "enum": [
        "A",
        "B",
        "C",
        "D"
      ]
    }
  }
}
